simpful/__init__.py
simpful/fuzzy_aggregation.py
simpful/fuzzy_sets.py
simpful/rule_parsing.py
simpful/simpful.py
simpful-2.11.1.dist-info/LICENSE
simpful-2.11.1.dist-info/METADATA
simpful-2.11.1.dist-info/WHEEL
simpful-2.11.1.dist-info/top_level.txt
simpful-2.11.1.dist-info/RECORD
