Metadata-Version: 2.1
Name: simpful
Version: 2.11.1
Summary: A user-friendly Python library for fuzzy logic
Home-page: https://github.com/aresio/simpful
Author: Marco S. Nobile
Author-email: marco.nobile@unive.it
License: LICENSE.txt
Keywords: fuzzy logic,sugeno,mamdani,reasoner,python,modeling
Classifier: Programming Language :: Python :: 3
Classifier: License :: OSI Approved :: GNU General Public License v3 (GPLv3)
Classifier: Operating System :: OS Independent
License-File: LICENSE
Requires-Dist: numpy >=1.12.0
Requires-Dist: scipy >=1.0.0
Provides-Extra: plotting
Requires-Dist: matplotlib >=3.5.1 ; extra == 'plotting'
Requires-Dist: seaborn >=0.11.2 ; extra == 'plotting'
